fibonacci_calculator_onion/__init__.py
fibonacci_calculator_onion/cli.py
fibonacci_calculator_onion/fibonacci_calculator_onion.py
fibonacci_calculator_onion/fibonacci_service.py
fibonacci_calculator_onion/fibonacci_table.py
fibonacci_calculator_onion-0.0.4.dist-info/AUTHORS.rst
fibonacci_calculator_onion-0.0.4.dist-info/LICENSE
fibonacci_calculator_onion-0.0.4.dist-info/METADATA
fibonacci_calculator_onion-0.0.4.dist-info/WHEEL
fibonacci_calculator_onion-0.0.4.dist-info/entry_points.txt
fibonacci_calculator_onion-0.0.4.dist-info/top_level.txt
fibonacci_calculator_onion-0.0.4.dist-info/RECORD
