Metadata-Version: 2.1
Name: fibonacci-calculator-onion
Version: 0.0.4
Summary: This calculator gives the n-th fibonacci number, sequence of fibonacci numbers or an index.
Home-page: https://github.com/MaartenUijen/fibonacci_calculator_onion
Author: Maarten Uijen
Author-email: maarten.uijen@ordina.nl
License: MIT license
Keywords: fibonacci_calculator_onion
Platform: UNKNOWN
Classifier: Development Status :: 2 - Pre-Alpha
Classifier: Intended Audience :: Developers
Classifier: License :: OSI Approved :: MIT License
Classifier: Natural Language :: English
Classifier: Programming Language :: Python :: 3
Classifier: Programming Language :: Python :: 3.5
Classifier: Programming Language :: Python :: 3.6
Classifier: Programming Language :: Python :: 3.7
Classifier: Programming Language :: Python :: 3.8
Requires-Python: >=3.5
Requires-Dist: Click (>=7.0)
